AUTHORS
CHANGES.rst
CREDITS.rst
LICENSE
MANIFEST.in
README.rst
requirements-test.txt
setup.cfg
setup.py
awstools/__init__.py
awstools/application.py
awstools/cfntemplate.py
awstools/display.py
awstools.egg-info/PKG-INFO
awstools.egg-info/SOURCES.txt
awstools.egg-info/dependency_links.txt
awstools.egg-info/entry_points.txt
awstools.egg-info/not-zip-safe
awstools.egg-info/requires.txt
awstools.egg-info/top_level.txt
awstools/commands/__init__.py
awstools/commands/cfnautoscale.py
awstools/commands/cloudformation.py
awstools/commands/ec2ssh.py
awstools/fabric/__init__.py
awstools/tests/__init__.py
awstools/tests/functional/__init__.py
awstools/tests/functional/test_cfn.py
awstools/tests/functional/test_cfnas.py
awstools/tests/functional/test_ec2ssh.py
awstools/tests/functional/test_fabric.py
awstools/tests/unittests/__init__.py
awstools/tests/unittests/test_application.py
awstools/tests/unittests/test_applications.py
awstools/tests/unittests/test_awstools.py
awstools/tests/unittests/test_cfntemplate.py
awstools/tests/unittests/test_display.py
awstools/utils/__init__.py
awstools/utils/autoscale.py
awstools/utils/cloudformation.py
awstools/utils/ec2.py
scripts/ec2ssh