Metadata-Version: 1.1
Name: awstools
Version: 0.3.8
Summary: High level tools to manage an AWS infrastructure
Home-page: https://bitbucket.org/pior/awstools
Author: Pior Bastida
Author-email: pior@pbastida.net
License: GPL
Platform: UNKNOWN
Classifier: Intended Audience :: System Administrators
Classifier: Environment :: Console
Classifier: License :: OSI Approved :: GNU General Public License v3 or later (GPLv3+)
Classifier: Operating System :: POSIX :: Linux
Classifier: Programming Language :: Python
Classifier: Programming Language :: Python :: 2.7
